README.md
setup.cfg
setup.py
src/rmat.f90
src/rmat_sub.f90
telewavesim/__init__.py
telewavesim/conf.py
telewavesim/doc.py
telewavesim/elast.py
telewavesim/utils.py
telewavesim/wiggle.py
telewavesim.egg-info/PKG-INFO
telewavesim.egg-info/SOURCES.txt
telewavesim.egg-info/dependency_links.txt
telewavesim.egg-info/requires.txt
telewavesim.egg-info/top_level.txt
telewavesim/examples/0-Start-Here.ipynb
telewavesim/examples/Notebooks/sim_Prfs_Porter2011.ipynb
telewavesim/examples/Notebooks/sim_SKS.ipynb
telewavesim/examples/Notebooks/sim_obs_Audet2016.ipynb
telewavesim/examples/models/model_Audet2016.txt
telewavesim/examples/models/model_Porter2011.txt
telewavesim/examples/models/model_SKS.txt